code_props/__init__.py
code_props/analysis.py
code_props-0.1.0.dist-info/LICENSE
code_props-0.1.0.dist-info/WHEEL
code_props-0.1.0.dist-info/METADATA
code_props-0.1.0.dist-info/RECORD
